simple_logger/__init__.py
simple_logger/logger.py
fluent_simple_logger-0.1.10.dist-info/LICENSE
fluent_simple_logger-0.1.10.dist-info/METADATA
fluent_simple_logger-0.1.10.dist-info/WHEEL
fluent_simple_logger-0.1.10.dist-info/top_level.txt
fluent_simple_logger-0.1.10.dist-info/RECORD
