Metadata-Version: 2.1
Name: fluent_simple_logger
Version: 0.1.10
Summary: A simple logger library for Python.
Home-page: https://github.com/m1serybtw/simple_logger
Author: fluentdev
Author-email: m1@fluent.dev
Classifier: Programming Language :: Python :: 3
Classifier: License :: OSI Approved :: MIT License
Classifier: Operating System :: OS Independent
Requires-Python: >=3.6
License-File: LICENSE
